entrypoint/__init__.py
entrypoint/core.py
entrypoint/py.typed
entrypoint-2.0.3.dist-info/LICENSE
entrypoint-2.0.3.dist-info/METADATA
entrypoint-2.0.3.dist-info/WHEEL
entrypoint-2.0.3.dist-info/RECORD
