Metadata-Version: 2.1
Name: entrypoint
Version: 2.0.3
Summary: Decorated functions as entry points.
Home-page: https://github.com/nekitdev/entrypoint
License: MIT
Keywords: python,entrypoint,entry
Author: nekitdev
Requires-Python: >=3.8
Classifier: Development Status :: 5 - Production/Stable
Classifier: Intended Audience :: Developers
Classifier: License :: OSI Approved :: MIT License
Classifier: Operating System :: OS Independent
Classifier: Programming Language :: Python :: 3
Classifier: Programming Language :: Python :: 3.8
Classifier: Programming Language :: Python :: 3.9
Classifier: Programming Language :: Python :: 3.10
Classifier: Programming Language :: Python :: 3.11
Classifier: Programming Language :: Python :: 3.12
Classifier: Topic :: Utilities
Classifier: Typing :: Typed
Requires-Dist: attrs (>=23.2.0)
Requires-Dist: named (>=1.4.2)
Requires-Dist: typing-aliases (>=1.8.0)
Project-URL: Chat, https://nekit.dev/chat
Project-URL: Documentation, https://nekitdev.github.io/entrypoint
Project-URL: Funding, https://nekit.dev/funding
Project-URL: Issues, https://github.com/nekitdev/entrypoint/issues
Project-URL: Repository, https://github.com/nekitdev/entrypoint
